{"skeleton":{"width":340,"height":160.51,"fps":24,"spine":"3.6.0","hash":" ","name":"Armature"},"bones":[{"name":"root"},{"length":294,"x":-142.7,"y":-14.95,"rotation":-0.4769,"name":"图层_2","parent":"root"},{"length":75,"x":180.1208,"y":40.3006,"rotation":179.7185,"name":"图层_3","parent":"图层_2"},{"length":32,"x":83.0668,"y":2.801,"rotation":-177.7607,"name":"图层_5","parent":"图层_2"},{"x":48.1652,"y":-4.7352,"rotation":-0.4417,"name":"图层_4","parent":"图层_5"},{"length":34,"x":60.3461,"y":-27.0687,"rotation":178.2376,"name":"图层_5_拷贝","parent":"图层_5"},{"length":34,"x":60.8044,"y":28.7091,"rotation":-178.6793,"name":"图层_5_拷贝_2","parent":"图层_5_拷贝"},{"x":52.2227,"y":5.9816,"rotation":-178.6793,"name":"图层_4_拷贝","parent":"图层_5_拷贝"},{"length":33,"x":60.8494,"y":-28.8551,"rotation":175.343,"name":"bone","parent":"图层_5_拷贝_2"},{"x":51.5665,"y":-3.1912,"name":"图层_4_拷贝_2","parent":"图层_5_拷贝_2"},{"length":36,"x":62.5105,"y":35.1475,"rotation":-175.0878,"name":"bone1","parent":"bone"},{"x":54.5743,"y":1.9253,"rotation":3.3363,"name":"图层_4_拷贝2","parent":"bone"},{"x":54.5341,"y":3.9058,"rotation":178.4242,"name":"图层_4_拷贝_21","parent":"bone1"},{"x":8.9275,"y":-24.8009,"rotation":178.4242,"name":"图层_4_拷贝1","parent":"bone1"}],"slots":[{"name":"图层_2","bone":"图层_2","attachment":"开始/图层_2"},{"name":"图层_3","bone":"图层_3","attachment":"开始/图层_3"},{"name":"图层_4","bone":"图层_4","attachment":"开始/图层_4"},{"name":"图层_4_拷贝_2","bone":"图层_4_拷贝_2","attachment":"开始/图层_4_拷贝_2"},{"name":"图层_4_拷贝","bone":"图层_4_拷贝","attachment":"开始/图层_4_拷贝"},{"name":"图层_4_拷贝1","bone":"图层_4_拷贝1","attachment":"开始/图层_4_拷贝"},{"name":"图层_4_拷贝_21","bone":"图层_4_拷贝_21","attachment":"开始/图层_4_拷贝_2"},{"name":"图层_4_拷贝2","bone":"图层_4_拷贝2","attachment":"开始/图层_4_拷贝"},{"name":"图层_5","bone":"图层_5","attachment":"开始/图层_5"},{"name":"图层_5_拷贝","bone":"图层_5_拷贝","attachment":"开始/图层_5_拷贝"},{"name":"图层_5_拷贝_2","bone":"图层_5_拷贝_2","attachment":"开始/图层_5_拷贝_2"},{"name":"图层_5_拷贝1","bone":"bone","attachment":"开始/图层_5_拷贝"},{"name":"图层_51","bone":"bone1","attachment":"开始/图层_5"}],"skins":{"default":{"图层_2":{"开始/图层_2":{"name":"开始/图层_2","width":340,"height":104,"x":143.27,"y":38.56,"rotation":0.48}},"图层_5_拷贝_2":{"开始/图层_5_拷贝_2":{"name":"开始/图层_5_拷贝_2","width":48,"height":38,"x":14.94,"y":-7.24,"rotation":178.68}},"图层_4_拷贝_2":{"开始/图层_4_拷贝_2":{"name":"开始/图层_4_拷贝_2","width":16,"height":20,"x":-0.4,"y":5.12,"rotation":178.68}},"图层_4_拷贝_21":{"开始/图层_4_拷贝_2":{"name":"开始/图层_4_拷贝_2","width":16,"height":20,"x":0.12,"y":-3.38}},"图层_4_拷贝":{"开始/图层_4_拷贝":{"name":"开始/图层_4_拷贝","width":16,"height":20,"x":-1.35,"y":5.41,"rotation":178.68}},"图层_4_拷贝2":{"开始/图层_4_拷贝":{"name":"开始/图层_4_拷贝","width":16,"height":20,"x":-0.08,"y":-2.69}},"图层_4":{"开始/图层_4":{"name":"开始/图层_4","width":16,"height":20,"x":-0.76,"y":3.47,"rotation":178.68},"开始/图层_4_拷贝":{"name":"开始/图层_4_拷贝","width":16,"height":20,"x":-0.85,"y":3.04,"rotation":178.68}},"图层_3":{"开始/图层_3":{"name":"开始/图层_3","width":162,"height":48,"x":-1.27,"y":1.33,"rotation":-179.24}},"图层_5_拷贝":{"开始/图层_5_拷贝":{"name":"开始/图层_5_拷贝","width":48,"height":38,"x":17.7,"y":8.6}},"图层_5":{"开始/图层_5":{"name":"开始/图层_5","width":48,"height":38,"x":15.17,"y":-9.27,"rotation":178.24}},"图层_5_拷贝1":{"开始/图层_5_拷贝":{"name":"开始/图层_5_拷贝","width":48,"height":38,"x":17.78,"y":7.08,"rotation":3.34}},"图层_4_拷贝1":{"开始/图层_4_拷贝":{"name":"开始/图层_4_拷贝","width":16,"height":20,"x":0.36,"y":-3.59}},"图层_51":{"开始/图层_5":{"name":"开始/图层_5","width":48,"height":38,"x":17.13,"y":-4.96,"rotation":178.42}}}},"animations":{"newAnimation":{"bones":{"图层_3":{"rotate":[{"time":0,"angle":0},{"time":0.2083,"angle":1.35},{"time":0.4166,"angle":-2.9},{"time":0.6249,"angle":1.26},{"time":0.8332,"angle":-1.72}],"scale":[{"time":0,"x":1,"y":1},{"time":0.2083,"x":1.13,"y":1.13},{"time":0.4166,"x":1.13,"y":1.13},{"time":0.6249,"x":0.99,"y":0.99}],"shear":[{"time":0},{"time":0.2083},{"time":0.4166},{"time":0.6249},{"time":0.8332}]},"图层_5":{"translate":[{"time":0,"x":0.93,"y":-1.35},{"time":0.125,"x":0.93,"y":-1.35},{"time":0.2083,"x":0.93,"y":-9.57},{"time":0.4166,"x":0.93,"y":-28.77},{"time":0.5416,"x":0.93,"y":-28.77},{"time":0.6249,"x":0.93,"y":-33.2},{"time":0.8332,"x":0.93,"y":-57.07}]},"图层_4":{"translate":[{"time":0},{"time":0.25,"x":-10.52},{"time":0.4167,"x":-41.63,"y":-23.91},{"time":0.625,"x":-27.8,"y":-23.91},{"time":0.8333,"x":2.29,"y":-51.23}]},"图层_4_拷贝":{"translate":[{"time":0},{"time":0.2083,"x":20.79,"y":4.12}],"rotate":[{"time":0,"angle":0},{"time":0.2083,"angle":-48.7}],"shear":[{"time":0},{"time":0.2083}]},"图层_4_拷贝_2":{"translate":[{"time":0},{"time":0.4167},{"time":0.625,"x":11.72,"y":-6.63}],"rotate":[{"time":0,"angle":0},{"time":0.4167,"angle":1.35},{"time":0.625,"angle":42.25}],"scale":[{"time":0,"x":1,"y":1},{"time":0.4167,"x":1.13,"y":1.13}],"shear":[{"time":0},{"time":0.4167},{"time":0.625}]}},"slots":{"图层_4":{"attachment":[{"time":0,"name":"开始/图层_4"},{"time":0.4167,"name":"开始/图层_4_拷贝"},{"time":0.8334,"name":"开始/图层_4"}]},"图层_4_拷贝":{"color":[{"time":0,"color":"FFFFFFFF"},{"time":0.2083,"color":"FFFFFF00"}]},"图层_4_拷贝_2":{"color":[{"time":0,"color":"FFFFFFFF"},{"time":0.4167,"color":"FFFFFFFF"},{"time":0.625,"color":"FFFFFF00"}]},"图层_5":{"color":[{"time":0,"color":"FFFFFFFF"},{"time":0.125,"color":"FFFFFFFF"},{"time":0.4167,"color":"FFFFFF00"}]},"图层_5_拷贝":{"color":[{"time":0,"color":"FFFFFFFF"},{"time":0.3333,"color":"FFFFFFFF"},{"time":0.8333,"color":"FFFFFF00"}]},"图层_5_拷贝1":{"color":[{"time":0,"color":"FFFFFF00"},{"time":0.2917,"color":"FFFFFF00"},{"time":0.3334,"color":"FFFFFF7F"},{"time":0.3751,"color":"FFFFFFFF"}]},"图层_51":{"color":[{"time":0,"color":"FFFFFF00"},{"time":0.7083,"color":"FFFFFF0A"},{"time":0.75,"color":"FFFFFF7F"},{"time":0.7917,"color":"FFFFFFFF"}]},"图层_4_拷贝1":{"color":[{"time":0,"color":"FFFFFF00"},{"time":0.75,"color":"FFFFFF00"},{"time":0.7917,"color":"FFFFFF7F"},{"time":0.8334,"color":"FFFFFFFF"}]},"图层_4_拷贝_21":{"color":[{"time":0,"color":"FFFFFF00"},{"time":0.3333,"color":"FFFFFF00"},{"time":0.375,"color":"FFFFFF7F"},{"time":0.4167,"color":"FFFFFFFF"}]}}}}}